pslpython/__init__.py
pslpython/model.py
pslpython/partition.py
pslpython/predicate.py
pslpython/psl-runtime.jar
pslpython/rule.py
pslpython/runtime.py
pslpython/deeppsl/__init__.py
pslpython/deeppsl/model.py
pslpython/deeppsl/server.py
pslpython-2.4.0.dist-info/METADATA
pslpython-2.4.0.dist-info/WHEEL
pslpython-2.4.0.dist-info/top_level.txt
pslpython-2.4.0.dist-info/RECORD
