Metadata-Version: 2.1
Name: pslpython
Version: 2.4.0
Summary: A python inferface to the PSL SRL/ML software.
Home-page: https://psl.linqs.org
Author: LINQS
Author-email: psl-users@googlegroups.com
License: UNKNOWN
Keywords: PSL ML SRL
Platform: UNKNOWN
Classifier: Intended Audience :: Science/Research
Classifier: Intended Audience :: Developers
Classifier: License :: OSI Approved :: Apache Software License
Classifier: Operating System :: OS Independent
Classifier: Programming Language :: Python :: 3
Requires-Python: >=3.5
Requires-Dist: JPype1 ==1.4.0
Requires-Dist: pandas >=0.24.1
